edc_qareports/__init__.py
edc_qareports/admin_site.py
edc_qareports/apps.py
edc_qareports/auth_objects.py
edc_qareports/auths.py
edc_qareports/choices.py
edc_qareports/urls.py
edc_qareports/utils.py
edc_qareports/admin/__init__.py
edc_qareports/admin/note_modeladmin.py
edc_qareports/admin/qa_report_log_admin.py
edc_qareports/admin/qa_report_log_summary_admin.py
edc_qareports/forms/__init__.py
edc_qareports/forms/note_form.py
edc_qareports/migrations/0001_initial.py
edc_qareports/migrations/0002_rename_reportnote_qareportnote_and_more.py
edc_qareports/migrations/0003_alter_qareportnote_options_and_more.py
edc_qareports/migrations/0004_alter_qareportnote_status.py
edc_qareports/migrations/0005_edcpermissions.py
edc_qareports/migrations/0006_qareportlog.py
edc_qareports/migrations/0007_qareportlog_edc_qarepor_accesse_738ffe_idx.py
edc_qareports/migrations/0008_qareportlogsummary.py
edc_qareports/migrations/0009_auto_20240812_1918.py
edc_qareports/migrations/0010_auto_20240812_1918.py
edc_qareports/migrations/0011_auto_20240813_0219.py
edc_qareports/migrations/0012_alter_qareportnote_note.py
edc_qareports/migrations/0013_rename_qareportnote_note_and_more.py
edc_qareports/migrations/0014_alter_note_options_alter_note_status.py
edc_qareports/migrations/0015_alter_note_status.py
edc_qareports/migrations/0016_alter_note_options_alter_qareportlog_options.py
edc_qareports/migrations/0017_auto_20240816_0256.py
edc_qareports/migrations/__init__.py
edc_qareports/model_mixins/__init__.py
edc_qareports/model_mixins/note_model_mixin.py
edc_qareports/model_mixins/on_study_missing_values_model_mixin.py
edc_qareports/model_mixins/qa_report_model_mixin.py
edc_qareports/model_mixins/qa_reports_permissions.py
edc_qareports/modeladmin_mixins/__init__.py
edc_qareports/modeladmin_mixins/list_filters.py
edc_qareports/modeladmin_mixins/note_modeladmin_mixin.py
edc_qareports/modeladmin_mixins/on_study_missing_values_modeladmin_mixin.py
edc_qareports-1.0.4.dist-info/licenses/AUTHORS
edc_qareports-1.0.4.dist-info/licenses/LICENSE
edc_qareports-1.0.4.dist-info/METADATA
edc_qareports-1.0.4.dist-info/WHEEL
edc_qareports-1.0.4.dist-info/top_level.txt
edc_qareports-1.0.4.dist-info/RECORD
